clipextractor/__init__.py
clipextractor/clip_extractor.py
ClipExtractor-0.0.2.dist-info/METADATA
ClipExtractor-0.0.2.dist-info/WHEEL
ClipExtractor-0.0.2.dist-info/top_level.txt
ClipExtractor-0.0.2.dist-info/RECORD
