Metadata-Version: 2.1
Name: ClipExtractor
Version: 0.0.2
Summary: Art Image Captioning Extractor by using CLIP Models
Home-page: https://github.com/falahgs/
Author: Falahgs.G.Saleih
Author-email: falahgs07@gmail.com
License: MIT
Keywords: Keras,Tensorflow,Classification
Classifier: Programming Language :: Python :: 3
Classifier: License :: OSI Approved :: MIT License
Classifier: Operating System :: OS Independent
Requires-Python: >=3.6
Requires-Dist: ftfy
Requires-Dist: regex
Requires-Dist: tqdm
Requires-Dist: pytorch-lightning
Requires-Dist: einops
Requires-Dist: transformers
Requires-Dist: gitpython
Requires-Dist: timm (==0.4.12)
Requires-Dist: fairscale (==0.4.4)
